pokeditto/__init__.py
pokeditto/random_pokemon.py
Pokeaditto_base-1.0.1.dist-info/METADATA
Pokeaditto_base-1.0.1.dist-info/WHEEL
Pokeaditto_base-1.0.1.dist-info/top_level.txt
Pokeaditto_base-1.0.1.dist-info/RECORD
