Metadata-Version: 2.1
Name: Pokeaditto-base
Version: 1.0.1
Summary: libreria para generar un pokemon aleatorio
Author: Brian Flores
Author-email: 20224036_flores@tesch.edu.mx
Requires-Dist: pandas
